{
  "project_info": {
    "project_number": "820090700637",
    "firebase_url": "https://vehishare-bcfba-default-rtdb.firebaseio.com",
    "project_id": "vehishare-bcfba",
    "storage_bucket": "vehishare-bcfba.appspot.com"
  },
  "client": [
    {
      "client_info": {
        "mobilesdk_app_id": "1:820090700637:android:00e71c0927e2e6510e5eb4",
        "android_client_info": {
          "package_name": "com.example.vehishare"
        }
      },
      "oauth_client": [
        {
          "client_id": "820090700637-t804ol0di3gcbeof8ncs90k6etbsadr4.apps.googleusercontent.com",
          "client_type": 3
        }
      ],
      "api_key": [
        {
          "current_key": "AIzaSyA31gaRJfUDfC1RkDCtIpsAfyIgz51LZQg"
        }
      ],
      "services": {
        "appinvite_service": {
          "other_platform_oauth_client": [
            {
              "client_id": "820090700637-t804ol0di3gcbeof8ncs90k6etbsadr4.apps.googleusercontent.com",
              "client_type": 3
            },
            {
              "client_id": "820090700637-fnetroijqao56f8s5o4lma2pek0te72o.apps.googleusercontent.com",
              "client_type": 2,
              "ios_info": {
                "bundle_id": "com.example.vehishare1.RunnerTests"
              }
            }
          ]
        }
      }
    }
  ],
  "configuration_version": "1"
}